version.py
cdisc_rules_engine/__init__.py
cdisc_rules_engine/plugin_loader.py
cdisc_rules_engine/rules_engine.py
cdisc_rules_engine/check_operators/__init__.py
cdisc_rules_engine/check_operators/dataframe_operators.py
cdisc_rules_engine/check_operators/helpers.py
cdisc_rules_engine/config/__init__.py
cdisc_rules_engine/config/config.py
cdisc_rules_engine/constants/__init__.py
cdisc_rules_engine/constants/adam_products.py
cdisc_rules_engine/constants/cache_constants.py
cdisc_rules_engine/constants/classes.py
cdisc_rules_engine/constants/data_structures.py
cdisc_rules_engine/constants/define_xml_constants.py
cdisc_rules_engine/constants/domains.py
cdisc_rules_engine/constants/metadata_columns.py
cdisc_rules_engine/constants/patterns.py
cdisc_rules_engine/constants/permissibility.py
cdisc_rules_engine/constants/rule_constants.py
cdisc_rules_engine/constants/use_cases.py
cdisc_rules_engine/dataset_builders/__init__.py
cdisc_rules_engine/dataset_builders/base_dataset_builder.py
cdisc_rules_engine/dataset_builders/content_metadata_dataset_builder.py
cdisc_rules_engine/dataset_builders/contents_dataset_builder.py
cdisc_rules_engine/dataset_builders/contents_define_dataset_builder.py
cdisc_rules_engine/dataset_builders/contents_define_variables_dataset_builder.py
cdisc_rules_engine/dataset_builders/contents_define_vlm_dataset_builder.py
cdisc_rules_engine/dataset_builders/dataset_builder_factory.py
cdisc_rules_engine/dataset_builders/dataset_metadata_define_dataset_builder.py
cdisc_rules_engine/dataset_builders/dataset_metadata_values_builder.py
cdisc_rules_engine/dataset_builders/define_item_group_dataset_builder.py
cdisc_rules_engine/dataset_builders/define_variables_dataset_builder.py
cdisc_rules_engine/dataset_builders/define_variables_with_library_metadata.py
cdisc_rules_engine/dataset_builders/domain_list_dataset_builder.py
cdisc_rules_engine/dataset_builders/json_schema_check_dataset_builder.py
cdisc_rules_engine/dataset_builders/jsonata_dataset_builder.py
cdisc_rules_engine-0.14.2.dist-info/licenses/LICENSE
cdisc_rules_engine-0.14.2.dist-info/METADATA
cdisc_rules_engine-0.14.2.dist-info/WHEEL
cdisc_rules_engine-0.14.2.dist-info/top_level.txt
cdisc_rules_engine-0.14.2.dist-info/RECORD
