Metadata-Version: 2.4
Name: cdisc-rules-engine
Version: 0.14.2
Summary: Open source offering of the cdisc rules engine
Author-email: cdisc-org <info@cdisc.org>
License: MIT
Project-URL: Homepage, https://github.com/cdisc-org/cdisc-rules-engine
Project-URL: Bug Tracker, https://github.com/cdisc-org/cdisc-rules-engine/issues
Requires-Python: <3.13,>=3.12
License-File: LICENSE
Requires-Dist: business_rules_enhanced==1.4.8
Requires-Dist: cachetools==6.1.0
Requires-Dist: cdisc-library-client==0.1.6
Requires-Dist: click==8.1.7
Requires-Dist: dask[dataframe]==2024.6.0
Requires-Dist: dask[array]==2024.6.0
Requires-Dist: fastparquet==2024.2.0
Requires-Dist: importlib-metadata==8.5.0
Requires-Dist: jsonata-python==0.6.0
Requires-Dist: jsonpath-ng==1.6.1
Requires-Dist: jsonschema==4.18.5
Requires-Dist: lxml==5.2.1
Requires-Dist: numpy~=1.26.0
Requires-Dist: odmlib==0.1.4
Requires-Dist: openpyxl==3.1.5
Requires-Dist: pandas==2.1.4
Requires-Dist: psutil==6.1.1
Requires-Dist: pyinstaller==6.11.0
Requires-Dist: Pympler==1.1
Requires-Dist: pyreadstat==1.2.7
Requires-Dist: python-dotenv==1.0.0
Requires-Dist: pyyaml==6.0.2
Requires-Dist: redis==4.5.0
Requires-Dist: requests~=2.32.3
Requires-Dist: setuptools~=75.6.0
Dynamic: license-file
